slgnn/__init__.py
slgnn-2024.8.27.dist-info/LICENSE
slgnn-2024.8.27.dist-info/METADATA
slgnn-2024.8.27.dist-info/WHEEL
slgnn-2024.8.27.dist-info/top_level.txt
slgnn-2024.8.27.dist-info/RECORD
