Metadata-Version: 2.1
Name: slgnn
Version: 2024.8.27
Summary: slgnn
Home-page: https://github.com/deepmaterials/slgnn
Author: Kamal Choudhary
Author-email: writetokamal.1989@gmail.com
Classifier: Programming Language :: Python :: 3
Classifier: License :: OSI Approved :: MIT License
Classifier: Operating System :: OS Independent
Requires-Python: >=3.9
License-File: LICENSE
Requires-Dist: numpy<2.0.0,>=1.19.5
Requires-Dist: scipy>=1.6.1
